{
  "teacher_id": "48865",
  "user_id": "81974085",
  "s_id": "70750-48865-81974085-1756551194083-1756551216161",
  "corp_id": "ww1234567890abcdef",
  "session_type": "1",
  "ip_position": "运营",
  "user_wx_id": "wmZx7_DAAAzMqGkXm1P6RNaDmnW6zwLg",
  "teacher_wx_id": "13434771190",
  "send_time": "2025-08-24T18:09:45+08:00",
  "department_name": "运营中心-客服部-综合服务-综合服务_深圳-综合服务_深圳_四组",
  "class_id": "70750",
  "context": [
    {
      "msg_id": "3456377994287168820_1756600963880_external",
      "session_id": "wmZx7_DAAAzMqGkXm1P6RNaDmnW6zwLg_13434771190",
      "msg_type": "text",
      "author": "老师",
      "content": "帮您核对下，您在叫叫APP看到【明日开课】的体验包了吗",
      "chat_time": "1756600963880",
      "if_sop_bi": "0",
      "valid": 1,
      "if_sop_strict": 0
    },
    {
      "msg_id": "3456377994287168830_1756600966827_external",
      "session_id": "wmZx7_DAAAzMqGkXm1P6RNaDmnW6zwLg_13434771190",
      "msg_type": "text",
      "author": "用户",
      "content": "有",
      "chat_time": "1756600966827",
      "if_sop_bi": "0",
      "valid": 1,
      "if_sop_strict": 0
    },
    {
      "msg_id": "3456377994287168876_1756600982794_external",
      "session_id": "wmZx7_DAAAzMqGkXm1P6RNaDmnW6zwLg_13434771190",
      "msg_type": "voice",
      "author": "老师",
      "content": "好的好的，那我就放心了，您也可以截图给我，我帮您核对一下课程，然后呢，您可以点开教教APP，在学习页面有学前必做，点开之后呢，是一个学前测评，您可以帮宝贝完成完成一下这个测评，方便我之后做一些针对性的指导。",
      "chat_time": "1756600982794",
      "if_sop_bi": "0",
      "valid": 1,
      "if_sop_strict": 0
    },
    {
      "msg_id": "3456377994287168919_1756600984688_external",
      "session_id": "wmZx7_DAAAzMqGkXm1P6RNaDmnW6zwLg_13434771190",
      "msg_type": "text",
      "author": "老师",
      "content": "咱们宝贝今年是上大班了吗？",
      "chat_time": "1756600984688",
      "if_sop_bi": "0",
      "valid": 1,
      "if_sop_strict": 0
    },
    {
      "msg_id": "3456377994287168999_1756601000572_external",
      "session_id": "wmZx7_DAAAzMqGkXm1P6RNaDmnW6zwLg_13434771190",
      "msg_type": "text",
      "author": "用户",
      "content": "没，下学期中班",
      "chat_time": "1756601000572",
      "if_sop_bi": "0",
      "valid": 1,
      "if_sop_strict": 0
    },
    {
      "msg_id": "3456377994287169059_1756600969390_external",
      "session_id": "wmZx7_DAAAzMqGkXm1P6RNaDmnW6zwLg_13434771190",
      "msg_type": "voice",
      "author": "老师",
      "content": "哦，这样啊，那还是挺适合的，我们的这个课程的话呢，就适合4~5岁这种中班大班的小朋友去阅读的，帮助宝贝做好一个幼小衔接的一个课程。",
      "chat_time": "1756600969390",
      "if_sop_bi": "0",
      "valid": 1,
      "if_sop_strict": 0
    },
    {
      "msg_id": "3456377994287169079_1756600997462_external",
      "session_id": "wmZx7_DAAAzMqGkXm1P6RNaDmnW6zwLg_13434771190",
      "msg_type": "text",
      "author": "老师",
      "content": "宝贝平常是怎么去阅读的啊",
      "chat_time": "1756600997462",
      "if_sop_bi": "0",
      "valid": 1,
      "if_sop_strict": 0
    },
    {
      "msg_id": "3456377994287169121_1756601023919_external",
      "session_id": "wmZx7_DAAAzMqGkXm1P6RNaDmnW6zwLg_13434771190",
      "msg_type": "text",
      "author": "老师",
      "content": "家长会马上开始，可以关注群消息啦~",
      "chat_time": "1756601023919",
      "if_sop_bi": "0",
      "valid": 1,
      "if_sop_strict": 0
    },
    {
      "msg_id": "3456377994287169172_1756601000912_external",
      "session_id": "wmZx7_DAAAzMqGkXm1P6RNaDmnW6zwLg_13434771190",
      "msg_type": "text",
      "author": "老师",
      "content": "⏰明天就开始阅读了，总结几点您认真查看~\n\n1️⃣明天随时15分钟即可完成，建议晨读，阅读+表达+识字都会锻炼到噢~\n2️⃣手机和平板都可以学，下载叫叫后用报名的【手机号码】登陆即可\n3️⃣我会关注宝贝的阅读情况，没有及时阅读也会进行监督提醒，希望您不会觉得打扰，感谢理解~\n\n五日阅读是个完整闭环，明天不要落下加油开个好头哟😊家长还有哪里不清楚的地方吗？",
      "chat_time": "1756601000912",
      "if_sop_bi": "0",
      "valid": 1,
      "if_sop_strict": 0
    },
    {
      "msg_id": "3456377994287169234_1756601010761_external",
      "session_id": "wmZx7_DAAAzMqGkXm1P6RNaDmnW6zwLg_13434771190",
      "msg_type": "image",
      "author": "老师",
      "content": "此消息是image类型",
      "chat_time": "1756601010761",
      "if_sop_bi": "0",
      "valid": 1,
      "if_sop_strict": 0
    },
    {
      "msg_id": "3456377994287169285_1756600992320_external",
      "session_id": "wmZx7_DAAAzMqGkXm1P6RNaDmnW6zwLg_13434771190",
      "msg_type": "text",
      "author": "老师",
      "content": "早呀☀宝宝起床后就可以阅读第一节童话《匹诺曹》了，学会诚实守信，积累表达三素句和汉字词汇，阅读量670字\n\n阅读方法：点进叫叫APP【学习】页面\n⭕一共4个环节，完成后分享【阅读报告】到群里，我会批阅点评",
      "chat_time": "1756600992320",
      "if_sop_bi": "0",
      "valid": 1,
      "if_sop_strict": 0
    },
    {
      "msg_id": "3456377994287169305_1756601004459_external",
      "session_id": "wmZx7_DAAAzMqGkXm1P6RNaDmnW6zwLg_13434771190",
      "msg_type": "voice",
      "author": "老师",
      "content": "宝贝，你好呀，我是娇娇阅读的九七老师，老师很高兴已经完成第一天的故事了，并且在表达环节回答较早的问题，反应也很迅速，答案也很准确嘛，看来今天的故事您有答认真完成哦，并且有在思考学期老师要给您点个大大的赞，那在答题闯关的部分呢，我们一定要听清楚叫叫的问题是什么，回想一下故事当中匹诺曹是怎么样去做的呢？待一会儿我们可以跟妈妈再复习一下，我相信你可以拿到更多的小星星的。接下来的阅读也希望您能够继续保持住，九七老师也会一直关注你的阅读表现的，我们一起加油吧。",
      "chat_time": "1756601004459",
      "if_sop_bi": "0",
      "valid": 1,
      "if_sop_strict": 0
    },
    {
      "msg_id": "3456377994287169360_1756601004980_external",
      "session_id": "wmZx7_DAAAzMqGkXm1P6RNaDmnW6zwLg_13434771190",
      "msg_type": "emotion",
      "author": "老师",
      "content": "此消息是emotion类型",
      "chat_time": "1756601004980",
      "if_sop_bi": "0",
      "valid": 1,
      "if_sop_strict": 0
    },
    {
      "msg_id": "3456377994287169420_1756600991258_external",
      "session_id": "wmZx7_DAAAzMqGkXm1P6RNaDmnW6zwLg_13434771190",
      "msg_type": "text",
      "author": "老师",
      "content": "妈妈可以把夸夸语音放给宝贝听一听，多表扬宝贝，强化学习行为哦，晚上我还准备了提问互动~",
      "chat_time": "1756600991258",
      "if_sop_bi": "0",
      "valid": 1,
      "if_sop_strict": 0
    },
    {
      "msg_id": "3456377994287169475_1756601053060_external",
      "session_id": "wmZx7_DAAAzMqGkXm1P6RNaDmnW6zwLg_13434771190",
      "msg_type": "text",
      "author": "老师",
      "content": "宝贝在表达环节非常不错哦 口吃很清晰，宝贝今年几岁了呀",
      "chat_time": "1756601053060",
      "if_sop_bi": "0",
      "valid": 1,
      "if_sop_strict": 0
    },
    {
      "msg_id": "3456377994287169524_1756600981475_external",
      "session_id": "wmZx7_DAAAzMqGkXm1P6RNaDmnW6zwLg_13434771190",
      "msg_type": "text",
      "author": "用户",
      "content": "快5周岁了",
      "chat_time": "1756600981475",
      "if_sop_bi": "0",
      "valid": 1,
      "if_sop_strict": 0
    },
    {
      "msg_id": "3456377994287169534_1756601081560_external",
      "session_id": "wmZx7_DAAAzMqGkXm1P6RNaDmnW6zwLg_13434771190",
      "msg_type": "text",
      "author": "老师",
      "content": "那还是挺棒的  表达这一块感觉比很多同龄的宝贝要好一些",
      "chat_time": "1756601081560",
      "if_sop_bi": "0",
      "valid": 1,
      "if_sop_strict": 0
    },
    {
      "msg_id": "3456377994287169550_1756601125499_external",
      "session_id": "wmZx7_DAAAzMqGkXm1P6RNaDmnW6zwLg_13434771190",
      "msg_type": "text",
      "author": "老师",
      "content": "小朋友平时是自己阅读吗？还是您在一旁指导[憨笑]",
      "chat_time": "1756601125499",
      "if_sop_bi": "0",
      "valid": 1,
      "if_sop_strict": 0
    },
    {
      "msg_id": "3456377994287169591_1756601026466_external",
      "session_id": "wmZx7_DAAAzMqGkXm1P6RNaDmnW6zwLg_13434771190",
      "msg_type": "text",
      "author": "用户",
      "content": "刚开始是我读给他听，现在偶尔他会读给我听",
      "chat_time": "1756601026466",
      "if_sop_bi": "0",
      "valid": 1,
      "if_sop_strict": 0
    },
    {
      "msg_id": "3456377994287169596_1756601058424_external",
      "session_id": "wmZx7_DAAAzMqGkXm1P6RNaDmnW6zwLg_13434771190",
      "msg_type": "text",
      "author": "老师",
      "content": "[强]怪不得呢，果然妈妈也是付出了很多精力呢",
      "chat_time": "1756601058424",
      "if_sop_bi": "0",
      "valid": 1,
      "if_sop_strict": 0
    },
    {
      "msg_id": "3456377994287169598_1756601080620_external",
      "session_id": "wmZx7_DAAAzMqGkXm1P6RNaDmnW6zwLg_13434771190",
      "msg_type": "text",
      "author": "老师",
      "content": "今天第一天阅读宝贝还适应吗",
      "chat_time": "1756601080620",
      "if_sop_bi": "0",
      "valid": 1,
      "if_sop_strict": 0
    },
    {
      "msg_id": "3456377994287169614_1756601148533_external",
      "session_id": "wmZx7_DAAAzMqGkXm1P6RNaDmnW6zwLg_13434771190",
      "msg_type": "text",
      "author": "用户",
      "content": "可以的",
      "chat_time": "1756601148533",
      "if_sop_bi": "0",
      "valid": 1,
      "if_sop_strict": 0
    },
    {
      "msg_id": "3456377994287169651_1756601032696_external",
      "session_id": "wmZx7_DAAAzMqGkXm1P6RNaDmnW6zwLg_13434771190",
      "msg_type": "voice",
      "author": "老师",
      "content": "那我就放心了，咱们的课程里面呢，不仅仅可以让宝贝去听故事，也会通过答题互动环节去引导小朋友思考表达的综合能力可以得到锻炼，对于之后宝贝各个科目的学习以及幼小衔接都是非常有帮助的。",
      "chat_time": "1756601032696",
      "if_sop_bi": "0",
      "valid": 1,
      "if_sop_strict": 0
    },
    {
      "msg_id": "3456377994287169693_1756601043828_external",
      "session_id": "wmZx7_DAAAzMqGkXm1P6RNaDmnW6zwLg_13434771190",
      "msg_type": "voice",
      "author": "老师",
      "content": "今天晚上8点呢，我也会在群里面去组织表达练习，宝贝妈妈这一会儿有时间的话，也可以带着宝宝积极的参与进来哦。",
      "chat_time": "1756601043828",
      "if_sop_bi": "0",
      "valid": 1,
      "if_sop_strict": 0
    },
    {
      "msg_id": "3456377994287169785_1756601017736_external",
      "session_id": "wmZx7_DAAAzMqGkXm1P6RNaDmnW6zwLg_13434771190",
      "msg_type": "text",
      "author": "用户",
      "content": "好，谢谢[玫瑰]",
      "chat_time": "1756601017736",
      "if_sop_bi": "0",
      "valid": 1,
      "if_sop_strict": 0
    },
    {
      "msg_id": "3456377994287169789_1756601033880_external",
      "session_id": "wmZx7_DAAAzMqGkXm1P6RNaDmnW6zwLg_13434771190",
      "msg_type": "emotion",
      "author": "老师",
      "content": "此消息是emotion类型",
      "chat_time": "1756601033880",
      "if_sop_bi": "0",
      "valid": 1,
      "if_sop_strict": 0
    },
    {
      "msg_id": "3456377994287169831_1756601054438_external",
      "session_id": "wmZx7_DAAAzMqGkXm1P6RNaDmnW6zwLg_13434771190",
      "msg_type": "image",
      "author": "老师",
      "content": "此消息是image类型",
      "chat_time": "1756601054438",
      "if_sop_bi": "0",
      "valid": 1,
      "if_sop_strict": 0
    },
    {
      "msg_id": "3456377994287169925_1756601120993_external",
      "session_id": "wmZx7_DAAAzMqGkXm1P6RNaDmnW6zwLg_13434771190",
      "msg_type": "text",
      "author": "老师",
      "content": "我先把刚做好的思维导图发您，整理了今天故事的阅读+表达+识字三方面重难点，可以帮孩子有逻辑的去梳理一遍故事内容~",
      "chat_time": "1756601120993",
      "if_sop_bi": "0",
      "valid": 1,
      "if_sop_strict": 0
    },
    {
      "msg_id": "3456377994287169957_1756601228256_external",
      "session_id": "wmZx7_DAAAzMqGkXm1P6RNaDmnW6zwLg_13434771190",
      "msg_type": "text",
      "author": "老师",
      "content": "你问我答”口才表达练习来咯！家长把我录的视频放孩子听，一共2个问题，多鼓励小朋友开口回答，慢慢练习表达哦~  \n视频给宝贝听一下哦😊每一次的开口都是对于宝贝表达的提升，在群里回答我吧！",
      "chat_time": "1756601228256",
      "if_sop_bi": "0",
      "valid": 1,
      "if_sop_strict": 0
    },
    {
      "msg_id": "3456377994287170003_1756601216064_external",
      "session_id": "wmZx7_DAAAzMqGkXm1P6RNaDmnW6zwLg_13434771190",
      "msg_type": "video",
      "author": "老师",
      "content": "此消息是video类型",
      "chat_time": "1756601216064",
      "if_sop_bi": "0",
      "valid": 1,
      "if_sop_strict": 0
    },
    {
      "msg_id": "3456377994287170075_1756601167790_external",
      "session_id": "wmZx7_DAAAzMqGkXm1P6RNaDmnW6zwLg_13434771190",
      "msg_type": "image",
      "author": "老师",
      "content": "此消息是image类型",
      "chat_time": "1756601167790",
      "if_sop_bi": "0",
      "valid": 1,
      "if_sop_strict": 0
    },
    {
      "msg_id": "3456377994287170165_1756601072814_external",
      "session_id": "wmZx7_DAAAzMqGkXm1P6RNaDmnW6zwLg_13434771190",
      "msg_type": "text",
      "author": "老师",
      "content": "早呀~宝贝昨天的阅读表现很棒哦，今天再坚持完成阅读就可以领取阅读小奖励啦！🎁，快来跟着主人公豆豆一起外出了解安全知识吧！\n\n⭕阅读量：650字\n⭕表达练习：复习“三要素”句式\n⭕识字：认识【水】字",
      "chat_time": "1756601072814",
      "if_sop_bi": "0",
      "valid": 1,
      "if_sop_strict": 0
    },
    {
      "msg_id": "3456377994287170245_1756601131048_external",
      "session_id": "wmZx7_DAAAzMqGkXm1P6RNaDmnW6zwLg_13434771190",
      "msg_type": "image",
      "author": "老师",
      "content": "此消息是image类型",
      "chat_time": "1756601131048",
      "if_sop_bi": "0",
      "valid": 1,
      "if_sop_strict": 0
    },
    {
      "msg_id": "3456377994287170342_1756601154785_external",
      "session_id": "wmZx7_DAAAzMqGkXm1P6RNaDmnW6zwLg_13434771190",
      "msg_type": "text",
      "author": "老师",
      "content": "今天坚持阅读老师也准备了一个小奖励哟！🎁\n👆思维导图我下午做好了，记得用起来，带宝贝去复习学到的汉字和表达句式~",
      "chat_time": "1756601154785",
      "if_sop_bi": "0",
      "valid": 1,
      "if_sop_strict": 0
    },
    {
      "msg_id": "3456377994287170371_1756601216296_external",
      "session_id": "wmZx7_DAAAzMqGkXm1P6RNaDmnW6zwLg_13434771190",
      "msg_type": "text",
      "author": "老师",
      "content": "睡前记得提醒宝贝学习落下的1节故事噢~，完成两节课程后，我会给宝贝发奖励的🎁",
      "chat_time": "1756601216296",
      "if_sop_bi": "0",
      "valid": 1,
      "if_sop_strict": 0
    },
    {
      "msg_id": "3456377994287170386_1756601187740_external",
      "session_id": "wmZx7_DAAAzMqGkXm1P6RNaDmnW6zwLg_13434771190",
      "msg_type": "image",
      "author": "老师",
      "content": "此消息是image类型",
      "chat_time": "1756601187740",
      "if_sop_bi": "0",
      "valid": 1,
      "if_sop_strict": 0
    },
    {
      "msg_id": "3456377994287170430_1756601028788_external",
      "session_id": "wmZx7_DAAAzMqGkXm1P6RNaDmnW6zwLg_13434771190",
      "msg_type": "text",
      "author": "老师",
      "content": "虽然宝贝还差一节故事，老师还是先把奖\n励发给你🙋‍\n这两节习惯养成故事，可以在行为敏感期帮助孩子自我管理，提高专注力",
      "chat_time": "1756601028788",
      "if_sop_bi": "0",
      "valid": 1,
      "if_sop_strict": 0
    },
    {
      "msg_id": "3456377994287170525_1756601134672_external",
      "session_id": "wmZx7_DAAAzMqGkXm1P6RNaDmnW6zwLg_13434771190",
      "msg_type": "text",
      "author": "老师",
      "content": "今天会带宝贝学习一节经典必读古诗《春夜喜雨》，用图像化的方式学古诗，小朋友更容易理解和记忆哦👏\n\n⭕ 掌握阅读方式：图像化记忆\n⭕ 汉字：“人”字及词汇\n\n（古诗难度加大，家长可以让小朋友跟唱或诵读，然后分享到群里哦）",
      "chat_time": "1756601134672",
      "if_sop_bi": "0",
      "valid": 1,
      "if_sop_strict": 0
    },
    {
      "msg_id": "3456377994287170557_1756601089774_external",
      "session_id": "wmZx7_DAAAzMqGkXm1P6RNaDmnW6zwLg_13434771190",
      "msg_type": "image",
      "author": "老师",
      "content": "此消息是image类型",
      "chat_time": "1756601089774",
      "if_sop_bi": "0",
      "valid": 1,
      "if_sop_strict": 0
    },
    {
      "msg_id": "3456377994287170612_1756601264765_external",
      "session_id": "wmZx7_DAAAzMqGkXm1P6RNaDmnW6zwLg_13434771190",
      "msg_type": "text",
      "author": "老师",
      "content": "1",
      "chat_time": "1756601264765",
      "if_sop_bi": "0",
      "valid": 1,
      "if_sop_strict": 0
    },
    {
      "msg_id": "3456377994287170619_1756601214000_external",
      "session_id": "wmZx7_DAAAzMqGkXm1P6RNaDmnW6zwLg_13434771190",
      "msg_type": "voice",
      "author": "老师",
      "content": "宝贝妈妈下午好呀，刚才检查宝贝的阅读报告，发现宝贝的话昨天和今天的课程都还没有来得及学哦，咱们这一块是时间上面不太方便吗？",
      "chat_time": "1756601214000",
      "if_sop_bi": "0",
      "valid": 1,
      "if_sop_strict": 0
    },
    {
      "msg_id": "3456377994287170664_1756601167158_external",
      "session_id": "wmZx7_DAAAzMqGkXm1P6RNaDmnW6zwLg_13434771190",
      "msg_type": "image",
      "author": "老师",
      "content": "此消息是image类型",
      "chat_time": "1756601167158",
      "if_sop_bi": "0",
      "valid": 1,
      "if_sop_strict": 0
    },
    {
      "msg_id": "3456377994287170689_1756601228312_external",
      "session_id": "wmZx7_DAAAzMqGkXm1P6RNaDmnW6zwLg_13434771190",
      "msg_type": "image",
      "author": "老师",
      "content": "此消息是image类型",
      "chat_time": "1756601228312",
      "if_sop_bi": "0",
      "valid": 1,
      "if_sop_strict": 0
    },
    {
      "msg_id": "3456377994287170727_1756601178278_external",
      "session_id": "wmZx7_DAAAzMqGkXm1P6RNaDmnW6zwLg_13434771190",
      "msg_type": "text",
      "author": "老师",
      "content": "这两天有很多家长也在咨询后期阅读安排？如何报名等等，想继续培养孩子阅读，您可以看一下我发的正式阅读资料👆\n \n⏰【明天上午10点】会在阅读群统一介绍本次开学季大促🔥阅读报名活动，全年力度最大的一次\n【预约参团】的人数越多福利越大，明天记得关注群消息噢～",
      "chat_time": "1756601178278",
      "if_sop_bi": "0",
      "valid": 1,
      "if_sop_strict": 0
    },
    {
      "msg_id": "3456377994287170731_1756601103668_external",
      "session_id": "wmZx7_DAAAzMqGkXm1P6RNaDmnW6zwLg_13434771190",
      "msg_type": "text",
      "author": "老师",
      "content": "马上还有十分钟阅读群“开学季大促”，开始正式预约啦~系统培养阅读能力、口才表达、识字量！预约家长优先享受“开学季大促”拼团活动福利！",
      "chat_time": "1756601103668",
      "if_sop_bi": "0",
      "valid": 1,
      "if_sop_strict": 0
    },
    {
      "msg_id": "3456377994287170769_1756601023505_external",
      "session_id": "wmZx7_DAAAzMqGkXm1P6RNaDmnW6zwLg_13434771190",
      "msg_type": "text",
      "author": "老师",
      "content": "家长，群内的阅读包已经介绍完毕！今日回复预约参与【开学季大促】拼团立享600元优惠券‼\n\n⭕原价2580元，暑期大促立减600元优惠=【1980元/年】👇 \n\n👉【240节互动阅读】\n👉【128本实体绘本】思维导图、练习题\n👉【176节随堂音频】\n👉【指导师服务】督学点评、班级活动\n👉【每周周总结，每月月测评】\n\n🔥🔥  预约满80人，享全年最大福利【买1赠9】\n\n🎁词典笔或护脊书包二选一（价值￥349）\n🎁实物礼包（小汽车收纳箱）\n🎁伴读VIP年卡（价值￥398,3-12岁适用)\n🎁20节益智故事赠课（价值￥299）\n🎁109节拓展音频故事\n🎁学习加油包（价值￥199）\n🎁家长大师课（价值￥418）\n🎁好友卡（价值￥108，亲友可享双周课程+绘本）\n🎁【年课1980】免单抽奖机会\n\n⭕支持30天无理由退款保障，退款仅扣除188元，实物赠品全部自留！\n\n🔥想要系统培养孩子阅读习惯，提升专注力+表达+思考+识字量，在群内回复【预约】即可参与“开学季大促”【买一赠九】活动！",
      "chat_time": "1756601023505",
      "if_sop_bi": "0",
      "valid": 1,
      "if_sop_strict": 0
    },
    {
      "msg_id": "3456377994287170793_1756601326682_external",
      "session_id": "wmZx7_DAAAzMqGkXm1P6RNaDmnW6zwLg_13434771190",
      "msg_type": "image",
      "author": "老师",
      "content": "此消息是image类型",
      "chat_time": "1756601326682",
      "if_sop_bi": "0",
      "valid": 1,
      "if_sop_strict": 0
    },
    {
      "msg_id": "3456377994287170827_1756601211147_external",
      "session_id": "wmZx7_DAAAzMqGkXm1P6RNaDmnW6zwLg_13434771190",
      "msg_type": "text",
      "author": "老师",
      "content": "应家长们的要求，我这边正在尝试申请额外加送全套《行为习惯+小主持人》课🎁，相当于报名再多一个月内容！有不清楚的都可以问我\n\n🔥想要享受最大福利报名给孩子系统培养阅读表达识字，在群内回复【预约】排队即可，不然无法享受“开学季大促”参团福利【买1赠10】噢~",
      "chat_time": "1756601211147",
      "if_sop_bi": "0",
      "valid": 1,
      "if_sop_strict": 0
    },
    {
      "msg_id": "3456377994287170867_1756601152376_external",
      "session_id": "wmZx7_DAAAzMqGkXm1P6RNaDmnW6zwLg_13434771190",
      "msg_type": "text",
      "author": "老师",
      "content": "1️⃣孩子3-6岁是语言发展的黄金期，错过不再有，现阶段孩子阅读能力是很强的，需要的是专业系统的体系来引导孩子，孩子的进步会非常快\n2️⃣孩子的兴趣是可以培养的，孩子现在不感兴趣，您就放弃，以后也不会喜欢阅读\n3️⃣一、二年级语文以记忆和背诵为主，学汉字、拼音、词句，没有太多输出和思维拓展；轻听说，重读写，老师更关注笔试成绩，忽略孩子表达能力。如果孩子从小没有阅读习惯，没有掌握阅读技巧，没有大量高质量的阅读输入，常说的三年级-分水岭就此形成，无数家长验证到时再补将事倍功半！ \n\n✅叫叫阅读承诺：提供【30天内无理由退款】，仅扣除首月服务费：188元，【寄给您的绘本和所有实物都不用退回，第一个月课程给您保留】。一个月足以看出有效果了，您根据效果再决定是退掉还是继续，叫叫给到家长最大的保障\n\n✨下午16点开团报名，【买1赠10】申请下来只有预约家长才能享受，群内回复【预约】抢占参团名额哦",
      "chat_time": "1756601152376",
      "if_sop_bi": "0",
      "valid": 1,
      "if_sop_strict": 0
    },
    {
      "msg_id": "3456377994287170954_1756601446334_external",
      "session_id": "wmZx7_DAAAzMqGkXm1P6RNaDmnW6zwLg_13434771190",
      "msg_type": "text",
      "author": "老师",
      "content": "📣团购报名正式开始，家长抓紧抢购全年最大福利【买1️⃣赠10】仅限前60位报名家长！！！\n\n购阅读年包赠送多重福利:\n🎁：全套《行为习惯+小主持》\n🎁词典笔或护脊书包二选一（价值￥349）\n🎁实物礼包（小汽车收纳箱）\n🎁伴读VIP年卡（价值￥398,3-12岁适用)\n🎁20节益智故事赠课（价值￥299）\n🎁109节拓展音频故事\n🎁学习加油包（价值￥199）\n🎁家长大师课（价值￥418）\n🎁好友卡（价值￥108，亲友可享双周课程+绘本）\n🎁【年课1980】免单抽奖机会\n👉享受30天试听，不满意退款仅扣188，首次快递全部自留，不过期\n直接点击下面对应链接，登录购课手机号，领券购买👇截图发群里好登记礼包\n⭕阅读2阶年课报名链接：https://tef8.cn/wu6ujZ",
      "chat_time": "1756601446334",
      "if_sop_bi": "0",
      "valid": 1,
      "if_sop_strict": 0
    },
    {
      "msg_id": "3456377994287170998_1756601108480_external",
      "session_id": "wmZx7_DAAAzMqGkXm1P6RNaDmnW6zwLg_13434771190",
      "msg_type": "text",
      "author": "老师",
      "content": "🔥暑期大促买一赠10最后17套‼\n🔥暑期大促买一赠10最后17套‼\n\n孩子养成好习惯宜早不宜迟，孩子成长真的很快，越大主观意识越强烈，现在黄金时期，30天都支持无理由退款，不合适也只扣188元，家长真的不趁暑假给孩子试试嘛？\n⭕带孩子尝试一下，宝贝肯定会给您惊喜的：https://tef8.cn/wu6ujZ",
      "chat_time": "1756601108480",
      "if_sop_bi": "0",
      "valid": 1,
      "if_sop_strict": 0
    },
    {
      "msg_id": "3456377994287171016_1756601420126_external",
      "session_id": "wmZx7_DAAAzMqGkXm1P6RNaDmnW6zwLg_13434771190",
      "msg_type": "text",
      "author": "老师",
      "content": "👉1980元=\n🌈二阶1980元阅读年包包含：\n1、240节 趣味阅读＋拓展回顾\n2、128 册图书绘本\n3、176节晚安音频\n4、109节拓展音频\n5、阅读礼包\n6、365天阅读指导师陪伴服务：专业指导、伴读、定期讲座\n\n买1️⃣赠🔟，赠送内容\n\n🎁：全套《行为习惯+小主持》\n🎁词典笔或护脊书包二选一（价值￥349）\n🎁实物礼包（小汽车收纳箱）\n🎁伴读VIP年卡（价值￥398,3-12岁适用)\n🎁20节益智故事赠课（价值￥299）\n🎁109节拓展音频故事\n🎁学习加油包（价值￥199）\n🎁家长大师课（价值￥418）\n🎁好友卡（价值￥108，亲友可享双周课程+绘本）\n🎁【年课1980】免单抽奖机会\n\n原价2580【⭕团购专享价格：1980/年】享30天无理由退款保障\n您可以看下包含的东西，全年报名最大优惠，内容一直有效不过期，幼儿园打好基础做好幼小过渡是非常有必要的，如果您想培养孩子的阅读能力，表达能力，识字能力，逻辑思维能力，一定要报名尝试！！\n⭕1980元【买1赠🔟】最后9套：https://tef8.cn/wu6ujZ",
      "chat_time": "1756601420126",
      "if_sop_bi": "0",
      "valid": 1,
      "if_sop_strict": 0
    },
    {
      "msg_id": "3456377994287171078_1756601427928_external",
      "session_id": "wmZx7_DAAAzMqGkXm1P6RNaDmnW6zwLg_13434771190",
      "msg_type": "image",
      "author": "老师",
      "content": "此消息是image类型",
      "chat_time": "1756601427928",
      "if_sop_bi": "0",
      "valid": 1,
      "if_sop_strict": 0
    },
    {
      "msg_id": "3456377994287171134_1756601222679_external",
      "session_id": "wmZx7_DAAAzMqGkXm1P6RNaDmnW6zwLg_13434771190",
      "msg_type": "text",
      "author": "老师",
      "content": "您是还在忙吗？买1赠🔟马上就清零了现在报名，绘本礼包明天就发货！\n\n现在学校都要求孩子每日阅读30分钟，暑假一定是打基础的最好时机，正好衔接新学期，咱们就利用30天试学保障给孩子试试嘛？",
      "chat_time": "1756601222679",
      "if_sop_bi": "0",
      "valid": 1,
      "if_sop_strict": 0
    },
    {
      "msg_id": "3456377994287171217_1756601333240_external",
      "session_id": "wmZx7_DAAAzMqGkXm1P6RNaDmnW6zwLg_13434771190",
      "msg_type": "text",
      "author": "老师",
      "content": "亲，咱们开团报名已经三个多小时了，看到您还没有给小朋友成功报名，是什么原因呀?\n再贵的学费➗365，都是很小的投资\n再小的学习✖365，都能拉开巨大差距\n\n现在趁活动报名，就算把第一个月课和40节赠送都学完了，两个月绘本、词典笔或护脊书包、小汽车收纳箱、阅读卡都自留，10月28日前想退款也只扣188元，试错的成本并不高！马上赠课清零了您一定抓住机会啊！\n⭕1980元年课报名链接（ 支持30天无理由退款）：https://tef8.cn/wu6ujZ",
      "chat_time": "1756601333240",
      "if_sop_bi": "0",
      "valid": 1,
      "if_sop_strict": 0
    },
    {
      "msg_id": "3456377994287171291_1756601169635_external",
      "session_id": "wmZx7_DAAAzMqGkXm1P6RNaDmnW6zwLg_13434771190",
      "msg_type": "text",
      "author": "老师",
      "content": "家长您有的顾虑和犹豫，我都觉得很正常，1980谁去买东西都得先考虑一下，那您想这是给孩子的教育投资，也不是买玩具零食，未来一年呢，您都不用单独给孩子再去报识字班，口才班，也不用单独去买绘本书，现在外面随随便便一本儿书都要十块钱，叫叫全年给您128本书都要1000多的，自己买书回去我们还很难坚持每天给孩子读，也很难做到在阅读中引导小朋友去思考，提升他的理解能力，对吧？而叫叫每天15分钟，孩子在阅读、表达、识字三方面都能同步去积累，有规划有方法孩子和您都会更加容易坚持，现在打好基础了之后孩子上小学他自己也更自信，学的更轻松嘛！\n\n买1️⃣赠🔟只剩最后的名额，咱们也有30天试听保障，最坏的结果就是您花188元，给孩子学了40线上课程+得到28本绘本+词典表/护脊书包+收纳小汽车，主题课很难申请，真的不希望咱们花了一样钱，比别人少了一个月20节阅读...是有什么顾虑回复下老师吧",
      "chat_time": "1756601169635",
      "if_sop_bi": "0",
      "valid": 1,
      "if_sop_strict": 0
    },
    {
      "msg_id": "3456377994287171330_1756601107296_external",
      "session_id": "wmZx7_DAAAzMqGkXm1P6RNaDmnW6zwLg_13434771190",
      "msg_type": "text",
      "author": "老师",
      "content": "试想一下1980元的费用放在银行也不会涨嘛，报名阅读，一天几块钱，至少宝贝可以有所收获，不合适就退嘛！\n\n现在我还没下班，可以登记上物流明天发货，明天就能接着学新内容\n1980元年课报名链接（ 支持30天无理由退款）：https://tef8.cn/wu6ujZ",
      "chat_time": "1756601107296",
      "if_sop_bi": "0",
      "valid": 1,
      "if_sop_strict": 0
    },
    {
      "msg_id": "3456377994287171368_1756601375819_external",
      "session_id": "wmZx7_DAAAzMqGkXm1P6RNaDmnW6zwLg_13434771190",
      "msg_type": "text",
      "author": "老师",
      "content": "一早起来很多家长说昨晚在忙确实没关注到，刚刚特意去公司申请了开通最后10套赠送试读期就是让您带孩子边学习边考虑！不合适也就只扣88元，现在报名还有收纳箱、词典笔/护脊书书包送\n\n⭕阅读2阶活动报名链接：https://tef8.cn/wu6ujZ（30天内支持无理由退款）\n您看到消息一定要回复一下噢，我也就不挂心了",
      "chat_time": "1756601375819",
      "if_sop_bi": "0",
      "valid": 1,
      "if_sop_strict": 0
    },
    {
      "msg_id": "3456377994287171380_1756601362224_external",
      "session_id": "wmZx7_DAAAzMqGkXm1P6RNaDmnW6zwLg_13434771190",
      "msg_type": "voice",
      "author": "老师",
      "content": "报好了吗？宝贝妈妈仓库已经在安排游戏绘本和礼包了哦，现在下单都还是有买一赠五的，错过就真的没有了。咱们现在报名一直到9月30号之前，退款都只扣88。上面所有的实体赠品您都是可以自留的，小朋友将近有两个月的时间可以去尝试，去看学习的效果呢。",
      "chat_time": "1756601362224",
      "if_sop_bi": "0",
      "valid": 1,
      "if_sop_strict": 0
    },
    {
      "msg_id": "3456377994287171467_1756601175395_external",
      "session_id": "wmZx7_DAAAzMqGkXm1P6RNaDmnW6zwLg_13434771190",
      "msg_type": "text",
      "author": "老师",
      "content": "再给您看下1980元全年阅读都包含什么吧？\n\n❣报名2阶年包可享：\n【240节线上互动阅读】\n【124册配套绘本+4古诗手册】\n【176节随堂故事音频】\n【全年导师伴读服务】\n【阅读，汉字，口才综合提升】\n\n本次大促活动买一赠10：\n🎁全套《行为习惯+小主持》\n🎁词典笔或护脊书包二选一（价值￥349）\n🎁实物礼包（小汽车收纳箱）\n🎁伴读VIP年卡（价值￥398,3-12岁适用)\n🎁20节益智故事赠课（价值￥299）\n🎁109节拓展音频故事\n🎁学习加油包（价值￥199）\n🎁家长大师课（价值￥418）\n🎁好友卡（价值￥108，亲友可享双周课程+绘本）\n🎁【年课1980】免单抽奖机会\n\n✅年课终身有效不过期！！享30天试听保障，不合适退款仅扣188，首次快递全部自留！\n\n平时给孩子买书也要花很多钱，何不去系统给孩子培养试试！最划算的一次活动，您抓紧时间购买👇\n⭕1980元年课报名链接：https://tef8.cn/wu6ujZ",
      "chat_time": "1756601175395",
      "if_sop_bi": "0",
      "valid": 1,
      "if_sop_strict": 0
    },
    {
      "msg_id": "3456377994287171485_1756601345840_external",
      "session_id": "wmZx7_DAAAzMqGkXm1P6RNaDmnW6zwLg_13434771190",
      "msg_type": "text",
      "author": "老师",
      "content": "没有哪个报名的家长是确定孩子能坚持才选择，都是抱着试一试的态度，无论咱们是有什么顾虑，我给您保证，本次绝对是最划算最物超所值的，相信我，给孩子先抢购上，实在不合适明天在app上退了都没问题\n\n我也觉得我很啰嗦，但是希望您让孩子试试再说，好吗🌹 \n❤二阶段报名链接（支持30天无理由退款）：https://tef8.cn/wu6ujZ",
      "chat_time": "1756601345840",
      "if_sop_bi": "0",
      "valid": 1,
      "if_sop_strict": 0
    }
  ],
  "chat_time_start": "1756551194083",
  "chat_time_end": "1756551216161"
}