{
  "teacher_id": "17244",
  "user_id": "81772579",
  "s_id": "70461-17244-81772579-1756879269905-1756879305889",
  "corp_id": "ww9876543210fedcba",
  "session_type": "1",
  "ip_position": "运营",
  "user_wx_id": "wmZx7_DAAAktNUDuODz9255g-zaNcWAA",
  "teacher_wx_id": "13228419398",
  "send_time": "2025-08-18T15:11:09+08:00",
  "department_name": "运营中心-客服部-综合服务-综合服务_深圳-综合服务_深圳_四组",
  "class_id": "70461",
  "context": [
    {
      "msg_id": "6141131108607148578_1756856936132_external",
      "session_id": "wmZx7_DAAAktNUDuODz9255g-zaNcWAA_13228419398",
      "msg_type": "text",
      "author": "老师",
      "content": "家长您好，明天就正式开启阅读体验了。开始前我想了解一下孩子的情况，以便针对性指导服务。请问：\n\n①咱们下载好叫叫App了吗？\n②平时有固定的阅读习惯吗？",
      "chat_time": "1756856936132",
      "if_sop_bi": "0",
      "valid": 1,
      "if_sop_strict": 0
    },
    {
      "msg_id": "6141131108607148591_1756856944519_external",
      "session_id": "wmZx7_DAAAktNUDuODz9255g-zaNcWAA_13228419398",
      "msg_type": "text",
      "author": "用户",
      "content": "下载好了",
      "chat_time": "1756856944519",
      "if_sop_bi": "0",
      "valid": 1,
      "if_sop_strict": 0
    },
    {
      "msg_id": "6141131108607148629_1756856948618_external",
      "session_id": "wmZx7_DAAAktNUDuODz9255g-zaNcWAA_13228419398",
      "msg_type": "text",
      "author": "用户",
      "content": "阅读的话我有时也做，就没那么坚持，",
      "chat_time": "1756856948618",
      "if_sop_bi": "0",
      "valid": 1,
      "if_sop_strict": 0
    },
    {
      "msg_id": "6141131108607148652_1756856944352_external",
      "session_id": "wmZx7_DAAAktNUDuODz9255g-zaNcWAA_13228419398",
      "msg_type": "text",
      "author": "老师",
      "content": "好的，下载好后用报名手机号码登录上，点到学习界面可以截图给我核对",
      "chat_time": "1756856944352",
      "if_sop_bi": "0",
      "valid": 1,
      "if_sop_strict": 0
    },
    {
      "msg_id": "6141131108607148653_1756856942876_external",
      "session_id": "wmZx7_DAAAktNUDuODz9255g-zaNcWAA_13228419398",
      "msg_type": "image",
      "author": "用户",
      "content": "此消息是image类型",
      "chat_time": "1756856942876",
      "if_sop_bi": "0",
      "valid": 1,
      "if_sop_strict": 0
    },
    {
      "msg_id": "6141131108607148734_1756856975117_external",
      "session_id": "wmZx7_DAAAktNUDuODz9255g-zaNcWAA_13228419398",
      "msg_type": "text",
      "author": "老师",
      "content": "这是一条引用/回复消息：\n\"阅读的话我有时也做，就没那么坚持，\"\n------\n了解了，小朋友开学是三年级对吧？",
      "chat_time": "1756856975117",
      "if_sop_bi": "0",
      "valid": 1,
      "if_sop_strict": 0
    },
    {
      "msg_id": "6141131108607148788_1756856954624_external",
      "session_id": "wmZx7_DAAAktNUDuODz9255g-zaNcWAA_13228419398",
      "msg_type": "text",
      "author": "用户",
      "content": "是的",
      "chat_time": "1756856954624",
      "if_sop_bi": "0",
      "valid": 1,
      "if_sop_strict": 0
    },
    {
      "msg_id": "6141131108607148794_1756856981674_external",
      "session_id": "wmZx7_DAAAktNUDuODz9255g-zaNcWAA_13228419398",
      "msg_type": "image",
      "author": "老师",
      "content": "此消息是image类型",
      "chat_time": "1756856981674",
      "if_sop_bi": "0",
      "valid": 1,
      "if_sop_strict": 0
    },
    {
      "msg_id": "6141131108607148891_1756856979108_external",
      "session_id": "wmZx7_DAAAktNUDuODz9255g-zaNcWAA_13228419398",
      "msg_type": "voice",
      "author": "老师",
      "content": "家长在下面这个学习页面找到明天开始的借口就是正确的。",
      "chat_time": "1756856979108",
      "if_sop_bi": "0",
      "valid": 1,
      "if_sop_strict": 0
    },
    {
      "msg_id": "6141131108607148922_1756857022226_external",
      "session_id": "wmZx7_DAAAktNUDuODz9255g-zaNcWAA_13228419398",
      "msg_type": "text",
      "author": "老师",
      "content": "这是一条引用/回复消息：\n\"是的\"\n------\n好的，三年级是一个比较重要的阶段，也就是咱们常说的分水岭，咱们本次带孩子体验，主要是想提升哪一方面呢？",
      "chat_time": "1756857022226",
      "if_sop_bi": "0",
      "valid": 1,
      "if_sop_strict": 0
    },
    {
      "msg_id": "6141131108607149021_1756856970472_external",
      "session_id": "wmZx7_DAAAktNUDuODz9255g-zaNcWAA_13228419398",
      "msg_type": "image",
      "author": "用户",
      "content": "此消息是image类型",
      "chat_time": "1756856970472",
      "if_sop_bi": "0",
      "valid": 1,
      "if_sop_strict": 0
    },
    {
      "msg_id": "6141131108607149087_1756856955712_external",
      "session_id": "wmZx7_DAAAktNUDuODz9255g-zaNcWAA_13228419398",
      "msg_type": "image",
      "author": "用户",
      "content": "此消息是image类型",
      "chat_time": "1756856955712",
      "if_sop_bi": "0",
      "valid": 1,
      "if_sop_strict": 0
    },
    {
      "msg_id": "6141131108607149176_1756856988488_external",
      "session_id": "wmZx7_DAAAktNUDuODz9255g-zaNcWAA_13228419398",
      "msg_type": "text",
      "author": "老师",
      "content": "这是一条引用/回复消息：\n\"[图片]\"\n------\n对的，这个页面就是正确的课程，明天解锁之后就可以阅读了",
      "chat_time": "1756856988488",
      "if_sop_bi": "0",
      "valid": 1,
      "if_sop_strict": 0
    },
    {
      "msg_id": "6141131108607149244_1756857042901_external",
      "session_id": "wmZx7_DAAAktNUDuODz9255g-zaNcWAA_13228419398",
      "msg_type": "text",
      "author": "用户",
      "content": "词汇量太少，认识也少",
      "chat_time": "1756857042901",
      "if_sop_bi": "0",
      "valid": 1,
      "if_sop_strict": 0
    },
    {
      "msg_id": "6141131108607149338_1756856965098_external",
      "session_id": "wmZx7_DAAAktNUDuODz9255g-zaNcWAA_13228419398",
      "msg_type": "voice",
      "author": "老师",
      "content": "好的，了解了，咱们这个课程就是帮助孩子提升词汇量的同时，也会给孩子教一些应试的方法跟技巧，因为上三年级之后，相较之前的二年级，他课外阅读量的量要求从之前6万字上升到了40万字左右，作文的要求也是从之前二年级的看图写话，现在要要求300字左右的命题式作文了，整体难度也是在上升。",
      "chat_time": "1756856965098",
      "if_sop_bi": "0",
      "valid": 1,
      "if_sop_strict": 0
    },
    {
      "msg_id": "6141131108607149376_1756857024362_external",
      "session_id": "wmZx7_DAAAktNUDuODz9255g-zaNcWAA_13228419398",
      "msg_type": "image",
      "author": "老师",
      "content": "此消息是image类型",
      "chat_time": "1756857024362",
      "if_sop_bi": "0",
      "valid": 1,
      "if_sop_strict": 0
    },
    {
      "msg_id": "6141131108607149377_1756857009412_external",
      "session_id": "wmZx7_DAAAktNUDuODz9255g-zaNcWAA_13228419398",
      "msg_type": "text",
      "author": "老师",
      "content": "课表您看下，四天课程会带着宝贝学到阅读理解、常考文章、常考典故、读后感写作的内容，能针对性强化薄弱环节，带孩子精读夯实基础，巩固课内[加油]",
      "chat_time": "1756857009412",
      "if_sop_bi": "0",
      "valid": 1,
      "if_sop_strict": 0
    },
    {
      "msg_id": "6141131108607149381_1756857079493_external",
      "session_id": "wmZx7_DAAAktNUDuODz9255g-zaNcWAA_13228419398",
      "msg_type": "text",
      "author": "老师",
      "content": "家长您好，稍后8点阅读群内家长会，您记得抽空关注一下：\n\n👉1.明天开课【全天任意抽15分钟即可】，确保下载好【叫叫】app，用报名手机号登录。\n👉2.请您打开【叫叫】app，下方【学习】核对您的上课界面是否如图↓显示明日开课。\n👉3.填写好北师大测评。\n",
      "chat_time": "1756857079493",
      "if_sop_bi": "0",
      "valid": 1,
      "if_sop_strict": 0
    },
    {
      "msg_id": "6141131108607149403_1756857046814_external",
      "session_id": "wmZx7_DAAAktNUDuODz9255g-zaNcWAA_13228419398",
      "msg_type": "image",
      "author": "老师",
      "content": "此消息是image类型",
      "chat_time": "1756857046814",
      "if_sop_bi": "0",
      "valid": 1,
      "if_sop_strict": 0
    },
    {
      "msg_id": "6141131108607149482_1756856993189_external",
      "session_id": "wmZx7_DAAAktNUDuODz9255g-zaNcWAA_13228419398",
      "msg_type": "text",
      "author": "老师",
      "content": "家长您好，咱们阅读群内正在召开阅读启动会，记得关注群消息哦[玫瑰]",
      "chat_time": "1756856993189",
      "if_sop_bi": "0",
      "valid": 1,
      "if_sop_strict": 0
    },
    {
      "msg_id": "6141131108607149537_1756857116512_external",
      "session_id": "wmZx7_DAAAktNUDuODz9255g-zaNcWAA_13228419398",
      "msg_type": "voice",
      "author": "老师",
      "content": "家长您好，您截图给我的页面是正确的，往下滑一下就能看到明天开始了。",
      "chat_time": "1756857116512",
      "if_sop_bi": "0",
      "valid": 1,
      "if_sop_strict": 0
    },
    {
      "msg_id": "6141131108607149618_1756857094178_external",
      "session_id": "wmZx7_DAAAktNUDuODz9255g-zaNcWAA_13228419398",
      "msg_type": "text",
      "author": "老师",
      "content": "这是一条引用/回复消息：\n\"[图片]\"\n------\n这个就是正确的",
      "chat_time": "1756857094178",
      "if_sop_bi": "0",
      "valid": 1,
      "if_sop_strict": 0
    },
    {
      "msg_id": "6141131108607149621_1756856964534_external",
      "session_id": "wmZx7_DAAAktNUDuODz9255g-zaNcWAA_13228419398",
      "msg_type": "text",
      "author": "老师",
      "content": "家长晚上好，课程明天更新全天可学！\n￵\n🔆早上是阅读的黄金时间，吸收最高效，希望小朋友养成晨读好习惯，能在这几天的阅读中有收获，期待明天的阅读表现哦~",
      "chat_time": "1756856964534",
      "if_sop_bi": "0",
      "valid": 1,
      "if_sop_strict": 0
    },
    {
      "msg_id": "6141131108607149681_1756857128987_external",
      "session_id": "wmZx7_DAAAktNUDuODz9255g-zaNcWAA_13228419398",
      "msg_type": "image",
      "author": "老师",
      "content": "此消息是image类型",
      "chat_time": "1756857128987",
      "if_sop_bi": "0",
      "valid": 1,
      "if_sop_strict": 0
    },
    {
      "msg_id": "6141131108607149720_1756857067532_external",
      "session_id": "wmZx7_DAAAktNUDuODz9255g-zaNcWAA_13228419398",
      "msg_type": "text",
      "author": "老师",
      "content": "早呀家长，今日课程已解锁\n\n需要您督宝贝学习，通过今天学习可以掌握比喻的基本概念和辨别真假比喻句，帮助宝贝在“比喻”上不再出错，轻松应试~\n\n快打开第一课《你以为你早就懂的比喻》学习吧，完成之后可以在群内打卡，我会一一点评哦！",
      "chat_time": "1756857067532",
      "if_sop_bi": "0",
      "valid": 1,
      "if_sop_strict": 0
    },
    {
      "msg_id": "6141131108607149786_1756857017832_external",
      "session_id": "wmZx7_DAAAktNUDuODz9255g-zaNcWAA_13228419398",
      "msg_type": "image",
      "author": "老师",
      "content": "此消息是image类型",
      "chat_time": "1756857017832",
      "if_sop_bi": "0",
      "valid": 1,
      "if_sop_strict": 0
    },
    {
      "msg_id": "6141131108607149809_1756857166570_external",
      "session_id": "wmZx7_DAAAktNUDuODz9255g-zaNcWAA_13228419398",
      "msg_type": "text",
      "author": "老师",
      "content": "家长下午好，小朋友已经坚持完成第一天的阅读，给小朋友点赞，好习惯的养成需要长期坚持，一定要继续保持哦",
      "chat_time": "1756857166570",
      "if_sop_bi": "0",
      "valid": 1,
      "if_sop_strict": 0
    },
    {
      "msg_id": "6141131108607149861_1756857042026_external",
      "session_id": "wmZx7_DAAAktNUDuODz9255g-zaNcWAA_13228419398",
      "msg_type": "text",
      "author": "老师",
      "content": "今天学习的是阅读理解中的识别真假比喻句，通过动画讲解的形式让孩子学会分析真假比喻的特点以及掌握如何分辨真假比较的技巧，在三年级上册的时候会经常用到，到时候可以灵活的运用起来",
      "chat_time": "1756857042026",
      "if_sop_bi": "0",
      "valid": 1,
      "if_sop_strict": 0
    },
    {
      "msg_id": "6141131108607149943_1756857030240_external",
      "session_id": "wmZx7_DAAAktNUDuODz9255g-zaNcWAA_13228419398",
      "msg_type": "image",
      "author": "老师",
      "content": "此消息是image类型",
      "chat_time": "1756857030240",
      "if_sop_bi": "0",
      "valid": 1,
      "if_sop_strict": 0
    },
    {
      "msg_id": "6141131108607149980_1756856999149_external",
      "session_id": "wmZx7_DAAAktNUDuODz9255g-zaNcWAA_13228419398",
      "msg_type": "text",
      "author": "老师",
      "content": "在练习环节小朋友错了8道题，需要家长您关注：\n今天内容是贯穿小初高的考点，考频高，分布广，其重要性不言而喻，课程模式采用“学”-“练”-“改”形成学习闭环，帮助孩子实现学科成绩和核心能力的提升",
      "chat_time": "1756856999149",
      "if_sop_bi": "0",
      "valid": 1,
      "if_sop_strict": 0
    },
    {
      "msg_id": "6141131108607149984_1756857127802_external",
      "session_id": "wmZx7_DAAAktNUDuODz9255g-zaNcWAA_13228419398",
      "msg_type": "text",
      "author": "老师",
      "content": "错题您也不用担心，后面几节课也会带着闭环练习，并且课上有专门改错环节，稍后您可以带着宝贝再巩固下",
      "chat_time": "1756857127802",
      "if_sop_bi": "0",
      "valid": 1,
      "if_sop_strict": 0
    },
    {
      "msg_id": "6141131108607150072_1756857143677_external",
      "session_id": "wmZx7_DAAAktNUDuODz9255g-zaNcWAA_13228419398",
      "msg_type": "text",
      "author": "老师",
      "content": "第一天学下来觉得感觉难度怎么样呀？能适应吗",
      "chat_time": "1756857143677",
      "if_sop_bi": "0",
      "valid": 1,
      "if_sop_strict": 0
    },
    {
      "msg_id": "6141131108607150125_1756857106564_external",
      "session_id": "wmZx7_DAAAktNUDuODz9255g-zaNcWAA_13228419398",
      "msg_type": "text",
      "author": "用户",
      "content": "还好",
      "chat_time": "1756857106564",
      "if_sop_bi": "0",
      "valid": 1,
      "if_sop_strict": 0
    },
    {
      "msg_id": "6141131108607150195_1756857192608_external",
      "session_id": "wmZx7_DAAAktNUDuODz9255g-zaNcWAA_13228419398",
      "msg_type": "voice",
      "author": "老师",
      "content": "那就很不错哦，因为有很多家长给我反馈说孩子觉得有点难，不知道咱们家小朋友有没有跟您说，因为这次学习的比喻句是三年级考试中的难点，咱们这次4天的课程会带着孩子闭环式学习，把整个比喻句的考点全部都吃透，今天的课是孩子自己学的还是您陪着的呀？",
      "chat_time": "1756857192608",
      "if_sop_bi": "0",
      "valid": 1,
      "if_sop_strict": 0
    },
    {
      "msg_id": "6141131108607150216_1756857056968_external",
      "session_id": "wmZx7_DAAAktNUDuODz9255g-zaNcWAA_13228419398",
      "msg_type": "text",
      "author": "用户",
      "content": "我在旁边，但我没说话",
      "chat_time": "1756857056968",
      "if_sop_bi": "0",
      "valid": 1,
      "if_sop_strict": 0
    },
    {
      "msg_id": "6141131108607150262_1756857010927_external",
      "session_id": "wmZx7_DAAAktNUDuODz9255g-zaNcWAA_13228419398",
      "msg_type": "voice",
      "author": "老师",
      "content": "嗯，好的，及时陪伴孩子阅读，能更好的关注孩子的学习状态，等到孩子思想跑锚的时候，也能及时的督促一下，那您一会儿记得带小朋友把错题再去巩固一下，打开今天的课程里边第三个环节就可以复习了。",
      "chat_time": "1756857010927",
      "if_sop_bi": "0",
      "valid": 1,
      "if_sop_strict": 0
    },
    {
      "msg_id": "6141131108607150340_1756857042692_external",
      "session_id": "wmZx7_DAAAktNUDuODz9255g-zaNcWAA_13228419398",
      "msg_type": "voice",
      "author": "老师",
      "content": "另外明天的课会给孩子教赏析比喻句的方法，整体难度也是比较大的，明天的课您也抽出一点时间来陪孩子一块儿完成，大概也是10多分钟左右，您看是有没有时间呢？",
      "chat_time": "1756857042692",
      "if_sop_bi": "0",
      "valid": 1,
      "if_sop_strict": 0
    },
    {
      "msg_id": "6141131108607150366_1756857203864_external",
      "session_id": "wmZx7_DAAAktNUDuODz9255g-zaNcWAA_13228419398",
      "msg_type": "text",
      "author": "用户",
      "content": "好的",
      "chat_time": "1756857203864",
      "if_sop_bi": "0",
      "valid": 1,
      "if_sop_strict": 0
    },
    {
      "msg_id": "6141131108607150371_1756857049220_external",
      "session_id": "wmZx7_DAAAktNUDuODz9255g-zaNcWAA_13228419398",
      "msg_type": "text",
      "author": "用户",
      "content": "有",
      "chat_time": "1756857049220",
      "if_sop_bi": "0",
      "valid": 1,
      "if_sop_strict": 0
    },
    {
      "msg_id": "6141131108607150392_1756857014561_external",
      "session_id": "wmZx7_DAAAktNUDuODz9255g-zaNcWAA_13228419398",
      "msg_type": "text",
      "author": "老师",
      "content": "好滴，有任何问题我们随时沟通哈，也看下宝贝的收获，的确看今天的学习报告，宝贝很认真，提升的空间也蛮大的，明天继续坚持[加油]",
      "chat_time": "1756857014561",
      "if_sop_bi": "0",
      "valid": 1,
      "if_sop_strict": 0
    },
    {
      "msg_id": "6141131108607150456_1756857277772_external",
      "session_id": "wmZx7_DAAAktNUDuODz9255g-zaNcWAA_13228419398",
      "msg_type": "image",
      "author": "老师",
      "content": "此消息是image类型",
      "chat_time": "1756857277772",
      "if_sop_bi": "0",
      "valid": 1,
      "if_sop_strict": 0
    },
    {
      "msg_id": "6141131108607150504_1756857115917_external",
      "session_id": "wmZx7_DAAAktNUDuODz9255g-zaNcWAA_13228419398",
      "msg_type": "text",
      "author": "老师",
      "content": "千里之行，始于足下🏃‍♂️ \n\n今天学习的比喻句是小学阶段考试常考的，也是小朋友很容易出错的，遇到会觉得很简单，但其实有着很多的细节\n\n这节课我们就将【比喻】拆分开来讲了讲，小朋友抽空可以打开下方知识总结复习一下哦👇",
      "chat_time": "1756857115917",
      "if_sop_bi": "0",
      "valid": 1,
      "if_sop_strict": 0
    },
    {
      "msg_id": "6141131108607150593_1756857183932_external",
      "session_id": "wmZx7_DAAAktNUDuODz9255g-zaNcWAA_13228419398",
      "msg_type": "text",
      "author": "老师",
      "content": "☀早上好，第二天的阅读开始啦~ \n\n👉第二节学习《你以为很难的比喻句赏析》，这节课就要带着宝贝去赏析比喻句啦，通过这节课的学习，之后再出现比喻相关的考试题目，宝贝都能轻松应对了~\n\n完成之后，阅读群内回复：第二天《比喻句赏析》已打卡✅\n期待小朋友今天的学习哦~ ",
      "chat_time": "1756857183932",
      "if_sop_bi": "0",
      "valid": 1,
      "if_sop_strict": 0
    },
    {
      "msg_id": "6141131108607150663_1756857306921_external",
      "session_id": "wmZx7_DAAAktNUDuODz9255g-zaNcWAA_13228419398",
      "msg_type": "image",
      "author": "老师",
      "content": "此消息是image类型",
      "chat_time": "1756857306921",
      "if_sop_bi": "0",
      "valid": 1,
      "if_sop_strict": 0
    },
    {
      "msg_id": "6141131108607150735_1756857115476_external",
      "session_id": "wmZx7_DAAAktNUDuODz9255g-zaNcWAA_13228419398",
      "msg_type": "file",
      "author": "老师",
      "content": "此消息是file类型",
      "chat_time": "1756857115476",
      "if_sop_bi": "0",
      "valid": 1,
      "if_sop_strict": 0
    },
    {
      "msg_id": "6141131108607150819_1756857127652_external",
      "session_id": "wmZx7_DAAAktNUDuODz9255g-zaNcWAA_13228419398",
      "msg_type": "text",
      "author": "老师",
      "content": "小朋友这两天的学习完成的非常不错哦，那么这里两天学到的【比喻】都是考试中常考的知识点，一定要记住哦，不会的可以在进行复习🌹\n\n这边也整理了一些小朋友需要的的知识点，希望对孩子有帮助🌹",
      "chat_time": "1756857127652",
      "if_sop_bi": "0",
      "valid": 1,
      "if_sop_strict": 0
    },
    {
      "msg_id": "6141131108607150890_1756857028500_external",
      "session_id": "wmZx7_DAAAktNUDuODz9255g-zaNcWAA_13228419398",
      "msg_type": "text",
      "author": "老师",
      "content": "家长晚上好，最近很多家长在咨询我后续的阅读内容。\n明天【下午2点】，我会在群里给大家进行统一的介绍，回复【预约】即可获得优惠拼团名额，您明天记得关注消息哦🌹",
      "chat_time": "1756857028500",
      "if_sop_bi": "0",
      "valid": 1,
      "if_sop_strict": 0
    },
    {
      "msg_id": "6141131108607150947_1756857147726_external",
      "session_id": "wmZx7_DAAAktNUDuODz9255g-zaNcWAA_13228419398",
      "msg_type": "image",
      "author": "老师",
      "content": "此消息是image类型",
      "chat_time": "1756857147726",
      "if_sop_bi": "0",
      "valid": 1,
      "if_sop_strict": 0
    },
    {
      "msg_id": "6141131108607151016_1756856985380_external",
      "session_id": "wmZx7_DAAAktNUDuODz9255g-zaNcWAA_13228419398",
      "msg_type": "text",
      "author": "老师",
      "content": "下面是全年内容详细安排👇家长可以点开图片原图查看哦～\n\n今天学习的【比喻句赏析】，一定要牢记，万能模板应对阅读理解赏析类题型，总结图片记得保存。",
      "chat_time": "1756856985380",
      "if_sop_bi": "0",
      "valid": 1,
      "if_sop_strict": 0
    },
    {
      "msg_id": "6141131108607151067_1756857316666_external",
      "session_id": "wmZx7_DAAAktNUDuODz9255g-zaNcWAA_13228419398",
      "msg_type": "image",
      "author": "老师",
      "content": "此消息是image类型",
      "chat_time": "1756857316666",
      "if_sop_bi": "0",
      "valid": 1,
      "if_sop_strict": 0
    },
    {
      "msg_id": "6141131108607151166_1756857415482_external",
      "session_id": "wmZx7_DAAAktNUDuODz9255g-zaNcWAA_13228419398",
      "msg_type": "image",
      "author": "老师",
      "content": "此消息是image类型",
      "chat_time": "1756857415482",
      "if_sop_bi": "0",
      "valid": 1,
      "if_sop_strict": 0
    },
    {
      "msg_id": "6141131108607151214_1756857421703_external",
      "session_id": "wmZx7_DAAAktNUDuODz9255g-zaNcWAA_13228419398",
      "msg_type": "text",
      "author": "老师",
      "content": "早上好~不知不觉来到第三天的课程啦，今天宝贝就要学习《晏子使楚》啦\n\n✅上课方式：打开【叫叫】学习软件，点击【开始】第三课《晏子使楚》学习吧，完成之后记得打卡哦~\n\n今天下午两点会介绍系统课程，可以关注一下[OK]",
      "chat_time": "1756857421703",
      "if_sop_bi": "0",
      "valid": 1,
      "if_sop_strict": 0
    },
    {
      "msg_id": "6141131108607151294_1756857379640_external",
      "session_id": "wmZx7_DAAAktNUDuODz9255g-zaNcWAA_13228419398",
      "msg_type": "image",
      "author": "老师",
      "content": "此消息是image类型",
      "chat_time": "1756857379640",
      "if_sop_bi": "0",
      "valid": 1,
      "if_sop_strict": 0
    },
    {
      "msg_id": "6141131108607151338_1756857008318_external",
      "session_id": "wmZx7_DAAAktNUDuODz9255g-zaNcWAA_13228419398",
      "msg_type": "text",
      "author": "老师",
      "content": "[玫瑰]家长下午好，咱们群内(1177期)即将介绍正式包\n\n👉下学期开始语文难度还会大幅提升，如果家长想孩子提升阅读理解、写作不轻易丢分，记得准时关注下群消息哦，团购福利大～",
      "chat_time": "1756857008318",
      "if_sop_bi": "0",
      "valid": 1,
      "if_sop_strict": 0
    },
    {
      "msg_id": "6141131108607151423_1756857080366_external",
      "session_id": "wmZx7_DAAAktNUDuODz9255g-zaNcWAA_13228419398",
      "msg_type": "text",
      "author": "老师",
      "content": "第6阶段全年系统包原价2580元\n🎁【团购价1980元】❗❗❗\n\n包含：\n✅ 【227节线上互动课程】含：64次阅读&写作技巧课+60次阅读积累课+20次周内同步练习+每日同步练（全年3000+练习量）+12次月度综合检测+71节寒暑假专项提升\n✅ 【学&练&拓&测】闭环学习，校内知识、应试能力、综合能力多维度同步提升\n✅ 【365天】阅读指导师专业伴读服务\n\n～～～～～～～～～～～～\n⭕福利：系统包享30天不满意无理由退费权益！！！\n\n如没有疑问，想给孩子规划系统写作阅读，请在群内回复【预约】\n预约人数越多，活动福利越大！",
      "chat_time": "1756857080366",
      "if_sop_bi": "0",
      "valid": 1,
      "if_sop_strict": 0
    },
    {
      "msg_id": "6141131108607151467_1756857089252_external",
      "session_id": "wmZx7_DAAAktNUDuODz9255g-zaNcWAA_13228419398",
      "msg_type": "text",
      "author": "老师",
      "content": "家长，您在忙还没看到消息吗？我已经写邮件给大家申请加赠名额了[愉快]\n现在1980报名前40人可享【买一赠六】👇\n\n🎁赠①：【阅读启航大礼包】（实物包邮到家）\n🎁赠②：【叫叫伴读vip权益会员，包含141节校内统编同步课】价值398元\n🎁赠③：【24节阅读基础大闯关】\n🎁赠④：【16节寓言里的小古文】\n🎁赠⑤：【写作全年包】\n🎁赠⑥：【两次北师大少儿中文阅读能力测评】价值399元\n\n如果您无疑问，想给孩子继续培养阅读能力以及写作技巧，请一定回复【预约+目前年级】匹配合适阶段开通专属报名通道，稍后开启团购。",
      "chat_time": "1756857089252",
      "if_sop_bi": "0",
      "valid": 1,
      "if_sop_strict": 0
    },
    {
      "msg_id": "6141131108607151510_1756857248220_external",
      "session_id": "wmZx7_DAAAktNUDuODz9255g-zaNcWAA_13228419398",
      "msg_type": "image",
      "author": "老师",
      "content": "此消息是image类型",
      "chat_time": "1756857248220",
      "if_sop_bi": "0",
      "valid": 1,
      "if_sop_strict": 0
    },
    {
      "msg_id": "6141131108607151546_1756857493877_external",
      "session_id": "wmZx7_DAAAktNUDuODz9255g-zaNcWAA_13228419398",
      "msg_type": "text",
      "author": "老师",
      "content": "家长下午好，看您还没有回复预约参与拼团，是还有什么疑问或顾虑吗❓\n\n体验课已更新过半了，我们的课程会把各个语文考核板块按照科学的梯度拆分开来，单独训练，逐个击破，拿到语文高分，真正拥有良好的阅读写作能力！\n\n如果您没有疑问，想给孩子继续培养阅读能力以及写作技巧，回复【预约】，我帮您登记参团名额。♥",
      "chat_time": "1756857493877",
      "if_sop_bi": "0",
      "valid": 1,
      "if_sop_strict": 0
    },
    {
      "msg_id": "6141131108607151633_1756857284886_external",
      "session_id": "wmZx7_DAAAktNUDuODz9255g-zaNcWAA_13228419398",
      "msg_type": "text",
      "author": "老师",
      "content": "家长您好~赠品名额已经申请下来了❗❗ ❗ \n咱们一共预约了87位家长，⏰晚上八点开启团购\n️今晚报名即享受拼团价格1980➕买1赠6福利\n——————————\n🎁赠①：【阅读启航大礼包】（实物包邮到家）\n🎁赠②：【叫叫伴读vip权益会员，包含141节校内统编同步课】价值398元\n🎁赠③：【24节阅读基础大闯关】\n🎁赠④：【16节寓言里的小古文】\n🎁赠⑤：【写作全年包】\n🎁赠⑥：【两次北师大少儿中文阅读能力测评】价值399元\n\n--------------------\n以上赠品仅限报名前60位\n✅您这边还没给孩子预约，群内回复：预约\n我帮您开通优惠权限\n",
      "chat_time": "1756857284886",
      "if_sop_bi": "0",
      "valid": 1,
      "if_sop_strict": 0
    },
    {
      "msg_id": "6141131108607151656_1756857183106_external",
      "session_id": "wmZx7_DAAAktNUDuODz9255g-zaNcWAA_13228419398",
      "msg_type": "text",
      "author": "老师",
      "content": "马上快8点了，家长还没考虑好吗？咱们今天所有的赠送和礼包都是限时限量的，仅限报名前60位，如果您还在纠结考虑，可以给宝贝先试一下的，不满意只扣88元，试错成本并不高。[玫瑰]",
      "chat_time": "1756857183106",
      "if_sop_bi": "0",
      "valid": 1,
      "if_sop_strict": 0
    },
    {
      "msg_id": "6141131108607151692_1756857106892_external",
      "session_id": "wmZx7_DAAAktNUDuODz9255g-zaNcWAA_13228419398",
      "msg_type": "text",
      "author": "老师",
      "content": "【买一赠六】通道开启!\n\n\n优惠报名链接：https://tef8.cn/wtN9wG \n\n直接点击上方链接即可报名成功👆，报名成功【截图发在阅读群内】，我依次登记赠品。",
      "chat_time": "1756857106892",
      "if_sop_bi": "0",
      "valid": 1,
      "if_sop_strict": 0
    },
    {
      "msg_id": "6141131108607151723_1756857532956_external",
      "session_id": "wmZx7_DAAAktNUDuODz9255g-zaNcWAA_13228419398",
      "msg_type": "text",
      "author": "老师",
      "content": "家长，这是一条群发消息，如果您收到链接了，直接点链接购买，买一赠六已过半了。",
      "chat_time": "1756857532956",
      "if_sop_bi": "0",
      "valid": 1,
      "if_sop_strict": 0
    },
    {
      "msg_id": "6141131108607151744_1756857334544_external",
      "session_id": "wmZx7_DAAAktNUDuODz9255g-zaNcWAA_13228419398",
      "msg_type": "text",
      "author": "老师",
      "content": "打扰了，老师真诚希望您能带着宝贝坚持阅读，大语文时代，阅读能力就是学习能力，有句话说：“你读的越多知道的就越多，知道的越多就会越聪明。”现在报上【买一赠六】，也有30天试读保障，所以是真的不希望家长错过了.\n\n👉优惠报名链接： https://tef8.cn/wtN9wG",
      "chat_time": "1756857334544",
      "if_sop_bi": "0",
      "valid": 1,
      "if_sop_strict": 0
    },
    {
      "msg_id": "6141131108607151833_1756857468545_external",
      "session_id": "wmZx7_DAAAktNUDuODz9255g-zaNcWAA_13228419398",
      "msg_type": "text",
      "author": "老师",
      "content": "赠品即将下架❗ ❗ ❗ \n赠品即将下架❗ ❗ ❗ \n赠品即将下架❗ ❗ ❗ \n\n1.   227节 线上互动阅读（含71节对标校内专题训练）\n2.   精美大启航礼包包邮寄送到家\n3. 365天 指导师全程伴读服务\n4. 【30余种】阅读策略\n5. 每月月测评\n\n\n❤点击链接即可完成报名： https://tef8.cn/wtN9wG\n🎁买一赠六，30天不满意包退",
      "chat_time": "1756857468545",
      "if_sop_bi": "0",
      "valid": 1,
      "if_sop_strict": 0
    },
    {
      "msg_id": "6141131108607151837_1756857171780_external",
      "session_id": "wmZx7_DAAAktNUDuODz9255g-zaNcWAA_13228419398",
      "msg_type": "text",
      "author": "老师",
      "content": "🌹家长我也准备下班了，想给您再解释一下30天试读政策：\n报名后就可以开始带孩子学习，从正式开课算起30天内效果不满意支持无理由退费。\n\n🌹您截图为据，联系我立马安排原路退款，只扣除88元服务费，像我们给您赠送的40节阅读内容，孩子就算读完不会额外扣取费用，赠送的礼盒也不用寄回来，也不会额外扣取费用。\n\n🌹买一送六真的绝无仅有，真心建议您带孩子试试，我这边也快要下班了，您考虑好了点这个报名链接报名： https://tef8.cn/wtN9wG",
      "chat_time": "1756857171780",
      "if_sop_bi": "0",
      "valid": 1,
      "if_sop_strict": 0
    },
    {
      "msg_id": "6141131108607151936_1756857072502_external",
      "session_id": "wmZx7_DAAAktNUDuODz9255g-zaNcWAA_13228419398",
      "msg_type": "text",
      "author": "老师",
      "content": "家长您好，现在已经很晚了，今天也是最后一次打扰您了，不管您是出于什么原因，暂时还在考虑，我要跟您说的是，考虑真的不如先行动，我相信您带着孩子来体验咱们这个阅读写作，那肯定也是希望他能够在这方面有所提升的，对吧？短短的三四天还看不出很明显的效果这是肯定的，让您做不了这个决定我也能够理解。但就算进入清华北大这样的名校，您去体验四天也不会有速成的效果，你说是吧？所以说我们给到您的这个30天试读保障，哪怕您现在报名了，您正式开启阅读之后30天之内有任何不满意是可以选择无理由退费的。那家长为什么不让小朋友继续尝试一下呢？孩子站在岸上是永远学不会游泳的，所以说我们现在可以让孩子尝试起来，30天边学边看效果，您看怎么样呢？[玫瑰]",
      "chat_time": "1756857072502",
      "if_sop_bi": "0",
      "valid": 1,
      "if_sop_strict": 0
    },
    {
      "msg_id": "6141131108607152027_1756857532112_external",
      "session_id": "wmZx7_DAAAktNUDuODz9255g-zaNcWAA_13228419398",
      "msg_type": "text",
      "author": "老师",
      "content": "今天第四课【一叶障目】更新啦，记得阅读哦！\n\n❤ 家长您昨天太忙了没有给咱们孩子续订系统阅读吗？\n\n这边赠品一直帮您留着呢，您还想续订的话就回复一下\n\n30天不满意可退+赠品链接： https://tef8.cn/wtN9wG",
      "chat_time": "1756857532112",
      "if_sop_bi": "0",
      "valid": 1,
      "if_sop_strict": 0
    },
    {
      "msg_id": "6141131108607152058_1756857163329_external",
      "session_id": "wmZx7_DAAAktNUDuODz9255g-zaNcWAA_13228419398",
      "msg_type": "text",
      "author": "老师",
      "content": "宝贝家长，报名后【一直有效】，全天【任意时间段】都可以学习，现在报名是最划算的🔥\n\n30天试读期保障，如果觉得不合适可以无理由退费，只扣除首月费用88元🤝即使是退掉，赠送的礼包都不需要寄回，家长放心让宝贝尝试一下❤\n\n🎉含赠品报名通道： https://tef8.cn/wtN9wG",
      "chat_time": "1756857163329",
      "if_sop_bi": "0",
      "valid": 1,
      "if_sop_strict": 0
    },
    {
      "msg_id": "6141131108607152135_1756857460276_external",
      "session_id": "wmZx7_DAAAktNUDuODz9255g-zaNcWAA_13228419398",
      "msg_type": "image",
      "author": "老师",
      "content": "此消息是image类型",
      "chat_time": "1756857460276",
      "if_sop_bi": "0",
      "valid": 1,
      "if_sop_strict": 0
    },
    {
      "msg_id": "6141131108607152160_1756857608054_external",
      "session_id": "wmZx7_DAAAktNUDuODz9255g-zaNcWAA_13228419398",
      "msg_type": "text",
      "author": "老师",
      "content": "宝贝妈妈，体验课看形式，正式课看效果。叫叫通过【学-练-拓-测】的方式，形成学习闭环，提高孩子的阅读理解能力。\n\n试学30天不满意无理由退款只扣88，送的礼包不用退回。👇现在报名赠送以下福利：\n🎁赠①：【阅读启航大礼包】（实物包邮到家）\n🎁赠②：【叫叫伴读vip权益会员，包含141节校内统编同步课】价值398元\n🎁赠③：【24节阅读基础大闯关】\n🎁赠④：【16节寓言里的小古文】\n🎁赠⑤：【写作全年包】\n🎁赠⑥：【两次北师大少儿中文阅读能力测评】价值399元\n\n含赠品报名通道： https://tef8.cn/wtN9wG",
      "chat_time": "1756857608054",
      "if_sop_bi": "0",
      "valid": 1,
      "if_sop_strict": 0
    },
    {
      "msg_id": "6141131108607152234_1756857400932_external",
      "session_id": "wmZx7_DAAAktNUDuODz9255g-zaNcWAA_13228419398",
      "msg_type": "text",
      "author": "老师",
      "content": "宝贝家长现在报名是最划算的！我可以给您算一算您看看\n\n大家一起拼团肯定比之后一个人报名划算\n1980元包括👇：\n1.  227节 线上互动阅读（含71节对标校内专题训练）\n2.【30余种】阅读策略\n3.【365天阅读指导师伴读】跟进反馈，指导写作\n\n\n🔥30天不满意只扣88！！试错成本极低❗\n如果退费，相当于88块钱学一个月系统包！何妨一试？\n\n✅6阶段拼团优惠链接： https://tef8.cn/wtN9wG",
      "chat_time": "1756857400932",
      "if_sop_bi": "0",
      "valid": 1,
      "if_sop_strict": 0
    },
    {
      "msg_id": "6141131108607152284_1756857594515_external",
      "session_id": "wmZx7_DAAAktNUDuODz9255g-zaNcWAA_13228419398",
      "msg_type": "text",
      "author": "老师",
      "content": "宝贝妈妈，咱们考虑好了吗？\n\n写作和阅读是拉分最多的，多阅读、多学写作技巧肯定没坏处，小朋友也体验几天了，咱们不要让孩子断学呀让孩子试试，您觉得呢？\n（30天无理由退）优惠报名链接： https://tef8.cn/wtN9wG",
      "chat_time": "1756857594515",
      "if_sop_bi": "0",
      "valid": 1,
      "if_sop_strict": 0
    },
    {
      "msg_id": "6141131108607152323_1756857171932_external",
      "session_id": "wmZx7_DAAAktNUDuODz9255g-zaNcWAA_13228419398",
      "msg_type": "text",
      "author": "老师",
      "content": "家长您好, 我给您发送的消息看到了吗？\n\n🌼在咱们叫叫一天几块钱的投资，收获孩子阅读理解和写文章的能力培养；尽早的激发孩子潜力，以后省事的是家长自己呀~\n\n长达30天的试读！退一步来说，如果孩子确实不适应，家长可以申请退费，至少让孩子学了一个月阅读看看呀! 孩子的成长和收获绝对出乎家长的想象！\n\n现在报名还有周边礼包，还有赠送的48节线上内容，真的很划算啊!\n\n💥已经阅读4天了,不要让这4天的进步变成零哦!\n优惠报名链接：https://tef8.cn/wtN9wG",
      "chat_time": "1756857171932",
      "if_sop_bi": "0",
      "valid": 1,
      "if_sop_strict": 0
    }
  ],
  "chat_time_start": "1756879269905",
  "chat_time_end": "1756879305889"
}